bondules/__init__.py
bondules/the_bon_library.py
bondules-1.0.1.dist-info/LICENSE.txt
bondules-1.0.1.dist-info/METADATA
bondules-1.0.1.dist-info/WHEEL
bondules-1.0.1.dist-info/top_level.txt
bondules-1.0.1.dist-info/RECORD
