Metadata-Version: 2.1
Name: bondules
Version: 1.0.1
Summary: Utility code created and used by Bon Crowder
Home-page: http://github.com/mathfour/bondules
Author: Bon Crowder @MathFour
Author-email: bon@mathfour.com
License: UNKNOWN
Keywords: pip,mathfour,utility,Bon Crowder
Platform: UNKNOWN
